odoo9_addon_l10n_es_aeat_sii-9.0.2.0.7-py2.7-nspkg.pth
odoo9_addon_l10n_es_aeat_sii-9.0.2.0.7.dist-info/DESCRIPTION.rst
odoo9_addon_l10n_es_aeat_sii-9.0.2.0.7.dist-info/METADATA
odoo9_addon_l10n_es_aeat_sii-9.0.2.0.7.dist-info/RECORD
odoo9_addon_l10n_es_aeat_sii-9.0.2.0.7.dist-info/WHEEL
odoo9_addon_l10n_es_aeat_sii-9.0.2.0.7.dist-info/metadata.json
odoo9_addon_l10n_es_aeat_sii-9.0.2.0.7.dist-info/namespace_packages.txt
odoo9_addon_l10n_es_aeat_sii-9.0.2.0.7.dist-info/top_level.txt
odoo_addons/l10n_es_aeat_sii/README.rst
odoo_addons/l10n_es_aeat_sii/__init__.py
odoo_addons/l10n_es_aeat_sii/__openerp__.py
odoo_addons/l10n_es_aeat_sii/hooks.py
odoo_addons/l10n_es_aeat_sii/data/aeat_sii_map_data.xml
odoo_addons/l10n_es_aeat_sii/data/aeat_sii_mapping_registration_keys_data.xml
odoo_addons/l10n_es_aeat_sii/data/ir_config_parameter.xml
odoo_addons/l10n_es_aeat_sii/i18n/bg.po
odoo_addons/l10n_es_aeat_sii/i18n/ca.po
odoo_addons/l10n_es_aeat_sii/i18n/cs.po
odoo_addons/l10n_es_aeat_sii/i18n/es.po
odoo_addons/l10n_es_aeat_sii/i18n/es_CO.po
odoo_addons/l10n_es_aeat_sii/i18n/es_CR.po
odoo_addons/l10n_es_aeat_sii/i18n/eu.po
odoo_addons/l10n_es_aeat_sii/i18n/fr.po
odoo_addons/l10n_es_aeat_sii/i18n/gl.po
odoo_addons/l10n_es_aeat_sii/i18n/hr.po
odoo_addons/l10n_es_aeat_sii/i18n/nl.po
odoo_addons/l10n_es_aeat_sii/i18n/pl.po
odoo_addons/l10n_es_aeat_sii/i18n/pt.po
odoo_addons/l10n_es_aeat_sii/i18n/pt_BR.po
odoo_addons/l10n_es_aeat_sii/i18n/ru.po
odoo_addons/l10n_es_aeat_sii/i18n/sl.po
odoo_addons/l10n_es_aeat_sii/i18n/sv.po
odoo_addons/l10n_es_aeat_sii/i18n/tr.po
odoo_addons/l10n_es_aeat_sii/i18n/vi.po
odoo_addons/l10n_es_aeat_sii/migrations/9.0.1.7.0/post-migration.py
odoo_addons/l10n_es_aeat_sii/models/__init__.py
odoo_addons/l10n_es_aeat_sii/models/account_fiscal_position.py
odoo_addons/l10n_es_aeat_sii/models/account_invoice.py
odoo_addons/l10n_es_aeat_sii/models/account_invoice_tax.py
odoo_addons/l10n_es_aeat_sii/models/aeat_sii.py
odoo_addons/l10n_es_aeat_sii/models/aeat_sii_map.py
odoo_addons/l10n_es_aeat_sii/models/aeat_sii_mapping_registration_keys.py
odoo_addons/l10n_es_aeat_sii/models/product_product.py
odoo_addons/l10n_es_aeat_sii/models/queue_job.py
odoo_addons/l10n_es_aeat_sii/models/res_company.py
odoo_addons/l10n_es_aeat_sii/models/res_partner.py
odoo_addons/l10n_es_aeat_sii/security/aeat_sii.xml
