Metadata-Version: 2.0
Name: odoo9-addon-l10n-es-aeat-sii
Version: 9.0.2.0.7
Summary: Suministro Inmediato de Información en el IVA
Home-page: https://odoospain.odoo.com
Author: Acysos S.L.,Diagram,Minorisa,Studio73,FactorLibre,Comunitea,Otherway,Tecnativa,Odoo Community Association (OCA)
Author-email: support@odoo-community.org
License: AGPL-3
Platform: UNKNOWN
Classifier: Programming Language :: Python
Classifier: Framework :: Odoo
Classifier: License :: OSI Approved :: GNU Affero General Public License v3
Requires-Python: ~=2.7
Requires-Dist: odoo (<9.1a,>=9.0a)
Requires-Dist: odoo9-addon-account-invoice-currency
Requires-Dist: odoo9-addon-account-invoice-refund-link
Requires-Dist: odoo9-addon-connector
Requires-Dist: odoo9-addon-l10n-es-aeat
Requires-Dist: pyOpenSSL (>=0.15)
Requires-Dist: requests
Requires-Dist: zeep
